_kiwipiepy.abi3.so
kiwipiepy/__init__.py
kiwipiepy/__main__.py
kiwipiepy/_c_api.py
kiwipiepy/_c_api.pyi
kiwipiepy/_version.py
kiwipiepy/_wrap.py
kiwipiepy/const.py
kiwipiepy/default_typo_transformer.py
kiwipiepy/documentation.md
kiwipiepy/knlm.py
kiwipiepy/sw_tokenizer.py
kiwipiepy/sw_trainer.py
kiwipiepy/template.py
kiwipiepy/transformers_addon.py
kiwipiepy/utils.py
kiwipiepy/corpus/stopwords.txt
kiwipiepy-0.22.2.dist-info/METADATA
kiwipiepy-0.22.2.dist-info/WHEEL
kiwipiepy-0.22.2.dist-info/top_level.txt
kiwipiepy-0.22.2.dist-info/RECORD
kiwipiepy-0.22.2.dist-info/licenses/LICENSE.txt
